{
  "customer_info": {
    "personal_info": [
      {
        "first_name": "John",
        "last_name": "Smith",
        "date_of_birth": "01/01/1980",
        "gender": "Male",
        "occupation": "Engineer",
        "identification_number": "34891021078800888"
      }
    ],
    "contact_info": [
      {
        "address": "123 Main St, Anytown USA 12345",
        "phone": "555-555-5555",
        "email": "johnsmith@example.com"
      }
    ]
  },
  "current_insurance_info": {
    "policy_number": "XYZ789",
    "coverage_amount": 50000,
    "coverage_type": "Term life insurance",
    "start_date": "01/01/2021",
    "end_date": "01/01/2022",
    "premium": 250
  },
  "new_insurance_info": {
    "policy_number": "ABC123",
    "coverage_amount": 100000,
    "coverage_type": "Term life insurance",
    "start_date": "01/01/2022",
    "end_date": "01/01/2023",
    "premium": 500
  },
  "kyc_documents": {
    "id_proof": [
      {
        "type": "Passport",
        "number": "123456789",
        "expiry_date": "01/01/2025",
        "scan": "https://i.pinimg.com/originals/1d/85/6b/1d856bbc4d39f25f05a114d5d4590f3a.jpg"
      }
    ],
    "address_proof": [
      {
        "type": "Utility Bill",
        "provider": "Electric Company",
        "issue_date": "01/01/2022",
        "scan": "https://files.jotform.com/jotformapps/utility-bill-template-6de9446af4f1724a198ee76f1ad6e470_og.png"
      }
    ]
  }
}
